{
  "meta": {
    "path": "03_Removal/Bubbly Babe/IMG_6442.MOV",
    "category": "removal",
    "shade": "Bubbly Babe",
    "duration": 6.2,
    "tokens_in": 1945,
    "tokens_out": 691,
    "cost": 0.0091
  },
  "record": {
    "clip_id": "IG-03-removal-bubbly-babe-img-6442",
    "product_line": "instant_gels",
    "category": "removal",
    "shade": "Bubbly Babe",
    "shade_matches_folder": true,
    "colour_finish": "pearl chrome nude pink",
    "shape": "squoval",
    "method": "tabs",
    "has_speech": false,
    "summary": "A close-up of a hand easily peeling off a pearlescent Bubbly Babe press-on nail, demonstrating damage-free removal.",
    "asmr": true,
    "segments": [
      {
        "t_start": 0.0,
        "t_end": 5.0,
        "usable": {
          "min": 0.0,
          "max": 5.0,
          "sweet_spot": 2.0
        },
        "action_climax": {
          "t": 2.5,
          "action": "peeling off the press-on nail from the index finger"
        },
        "creative_role": [
          "demo",
          "proof"
        ],
        "creative_stage": "Demo",
        "process_step": "removal_lift",
        "subject": "both_hands",
        "framing": "close_up",
        "camera": "static",
        "motion_level": "slow",
        "setting": "white background with shadow",
        "nail_position": "right",
        "text_safe_zones": [
          "left",
          "top_left",
          "bottom_left"
        ],
        "products_visible": [
          "press_on_set"
        ],
        "durability_test": "none",
        "asmr_moments": [
          {
            "t": 2.5,
            "desc": "soft click of the press-on nail lifting off"
          }
        ],
        "visual_fingerprint": "Oiled fingers on a white surface with a diagonal shadow, peeling off a pearlescent nude press-on nail.",
        "claims_shown": [
          "reusable"
        ],
        "safety_sensitive": false,
        "scores": {
          "visual_quality": 9,
          "product_visibility": 9,
          "hook": 8,
          "proof": 9,
          "standalone": 8,
          "edit_flexibility": 8
        },
        "search_tags": [
          "removal",
          "peel off",
          "bubbly babe",
          "damage free",
          "easy removal",
          "squoval nails",
          "nude shimmer"
        ],
        "confidence": 0.95,
        "human_review": false
      }
    ]
  },
  "compliance": {
    "verdict": "ok",
    "issues": []
  }
}